mdhk/auth.cpython-311-darwin.so
mdhk-1.0.14.dist-info/RECORD
mdhk-1.0.14.dist-info/WHEEL
mdhk-1.0.14.dist-info/top_level.txt
mdhk-1.0.14.dist-info/METADATA
