Metadata-Version: 2.4
Name: mdhk
Version: 1.0.14
Summary: Morden Fly add-ons manager for Blender
Author: MDHK
Requires-Python: >=3.11,<3.12
Dynamic: author
Dynamic: description
Dynamic: description-content-type
Dynamic: requires-python
Dynamic: summary
